gNet/__init__.py
gNet/activation_functions.py
gNet/conv_utils.py
gNet/initializer.py
gNet/layer.py
gNet/loss_functions.py
gNet/metric.py
gNet/model.py
gNet/neuralnetwork.py
gNet/optimizer.py
gNet/regularizer.py
gNet/tensor.py
gNet/tensor_ops.py
gNet/utils.py
gNet-0.2.1.1.dist-info/LICENSE
gNet-0.2.1.1.dist-info/METADATA
gNet-0.2.1.1.dist-info/WHEEL
gNet-0.2.1.1.dist-info/top_level.txt
gNet-0.2.1.1.dist-info/RECORD
