Metadata-Version: 2.1
Name: gNet
Version: 0.2.1.1
Summary: A mini Deep Learning Library
Home-page: https://github.com/MGokcayK/gNet
Author: Mehmet Gökçay Kabataş
Author-email: mgokcaykdev@gmail.com
License: MIT
Keywords: mini,deep learning
Platform: UNKNOWN
Classifier: Programming Language :: Python :: 3
Classifier: License :: OSI Approved :: MIT License
Classifier: Operating System :: OS Independent
Requires-Python: >=3.6
Requires-Dist: numpy (>=1.18.1)
Requires-Dist: matplotlib (>=3.1.2)
Requires-Dist: texttable (>=1.6.2)
Requires-Dist: wget (>=3.2)
Requires-Dist: idx2numpy (>=1.2.2)
